[{"artist":{"terms_freq":"1.0","id":"ARD7TVE1187B99BFB1","terms":"hip hop","name":"Casual","location":"California - LA","similar":"ARV4KO21187FB38008","familiarity":0.581793766,"longitude":-63.933357868519515,"latitude":37.15735675013362,"hotttnesss":0.401997543},"release":{"id":300848,"name":"Fear Itself"},"song":{"year":0,"title":"I Didn\u0027t Mean To","artist_mbtags":"","id":"SOMZWCG12A8C13C480","key":"1.0","duration":218.93179,"mode_confidence":0.636,"artist_mbtags_count":0.0,"key_confidence":0.736,"tatums_start":0.28519,"hotttnesss":0.60212,"beats_start":0.58521,"time_signature_confidence":0.778,"bars_confidence":0.643,"bars_start":0.58521,"start_of_fade_out":218.932,"tempo":92.198,"end_of_fade_in":0.247,"beats_confidence":0.834,"mode":0.0,"time_signature":4.0,"loudness":-11.197}},{"artist":{"terms_freq":"0.988583863","id":"AR7G5I41187FB4CE6C","terms":"pop rock","name":"Adam Ant","location":"London, England","similar":"AR4R0741187FB39AF2","familiarity":0.630382334,"longitude":-63.933357868519515,"latitude":37.15735675013362,"hotttnesss":0.454231157},"release":{"id":287650,"name":"Friend Or Foe"},"song":{"year":1982,"title":"Something Girls","artist_mbtags":"uk","id":"SONHOTT12A8C13493C","key":"0.0","duration":233.40363,"mode_confidence":0.749,"artist_mbtags_count":1.0,"key_confidence":0.751,"tatums_start":0.56254,"hotttnesss":0.0,"beats_start":0.81002,"time_signature_confidence":0.0,"bars_confidence":0.017,"bars_start":1.30621,"start_of_fade_out":217.124,"tempo":119.293,"end_of_fade_in":0.0,"beats_confidence":0.809,"mode":1.0,"time_signature":4.0,"loudness":-9.013}},{"artist":{"terms_freq":"1.0","id":"ARKFYS91187B98E58F","terms":"southern gospel","name":"Jeff And Sheri Easter","location":"Not available","similar":"ARHNMEZ11F50C4706C","familiarity":0.535292736,"longitude":-63.933357868519515,"latitude":37.15735675013362,"hotttnesss":0.385470551},"release":{"id":41838,"name":"Ordinary Day"},"song":{"year":0,"title":"The Moon And I (Ordinary Day Album Version)","artist_mbtags":"","id":"SOYMRWW12A6D4FAB14","key":"5.0","duration":267.7024,"mode_confidence":0.557,"artist_mbtags_count":0.0,"key_confidence":0.635,"tatums_start":0.53929,"hotttnesss":0.0,"beats_start":0.74856,"time_signature_confidence":0.454,"bars_confidence":0.121,"bars_start":1.17118,"start_of_fade_out":254.27,"tempo":147.782,"end_of_fade_in":2.264,"beats_confidence":0.438,"mode":1.0,"time_signature":3.0,"loudness":-9.323}}]